README.rst
setup.py
dprj/__init__.py
dprj.egg-info/PKG-INFO
dprj.egg-info/SOURCES.txt
dprj.egg-info/dependency_links.txt
dprj.egg-info/top_level.txt