Metadata-Version: 1.1
Name: dprj
Version: 0.1.0
Summary: Double-metaphone-like algorithm for the french language
Home-page: https://github.com/sephii/dprj
Author: Sylvain Fankhauser
Author-email: sylvain@fankhauser.name
License: MIT
Platform: UNKNOWN
Classifier: Development Status :: 4 - Beta
Classifier: Intended Audience :: Developers
Classifier: License :: OSI Approved :: MIT License
Classifier: Operating System :: OS Independent
Classifier: Programming Language :: Python :: 3.4
Classifier: Programming Language :: Python :: 2.7
